odoo10_addon_purchase_delivery_split_date-10.0.1.0.0-py2.7-nspkg.pth
odoo/addons/purchase_delivery_split_date/README.rst
odoo/addons/purchase_delivery_split_date/__init__.py
odoo/addons/purchase_delivery_split_date/__manifest__.py
odoo/addons/purchase_delivery_split_date/i18n/ca.po
odoo/addons/purchase_delivery_split_date/i18n/de.po
odoo/addons/purchase_delivery_split_date/i18n/es.po
odoo/addons/purchase_delivery_split_date/i18n/es_MX.po
odoo/addons/purchase_delivery_split_date/i18n/fi.po
odoo/addons/purchase_delivery_split_date/i18n/fr.po
odoo/addons/purchase_delivery_split_date/i18n/gl.po
odoo/addons/purchase_delivery_split_date/i18n/it.po
odoo/addons/purchase_delivery_split_date/i18n/pt_BR.po
odoo/addons/purchase_delivery_split_date/i18n/pt_PT.po
odoo/addons/purchase_delivery_split_date/i18n/ro.po
odoo/addons/purchase_delivery_split_date/i18n/sl.po
odoo/addons/purchase_delivery_split_date/models/__init__.py
odoo/addons/purchase_delivery_split_date/models/purchase.py
odoo/addons/purchase_delivery_split_date/tests/__init__.py
odoo/addons/purchase_delivery_split_date/tests/test_purchase_delivery.py
odoo10_addon_purchase_delivery_split_date-10.0.1.0.0.dist-info/DESCRIPTION.rst
odoo10_addon_purchase_delivery_split_date-10.0.1.0.0.dist-info/METADATA
odoo10_addon_purchase_delivery_split_date-10.0.1.0.0.dist-info/RECORD
odoo10_addon_purchase_delivery_split_date-10.0.1.0.0.dist-info/WHEEL
odoo10_addon_purchase_delivery_split_date-10.0.1.0.0.dist-info/metadata.json
odoo10_addon_purchase_delivery_split_date-10.0.1.0.0.dist-info/namespace_packages.txt
odoo10_addon_purchase_delivery_split_date-10.0.1.0.0.dist-info/top_level.txt
