Metadata-Version: 2.0
Name: odoo10-addon-purchase-delivery-split-date
Version: 10.0.1.0.0
Summary: Allows Purchase Order you confirm to generate one Incoming Shipment for each expected date indicated in the Purchase Order Lines
Home-page: UNKNOWN
Author: Numérigraphe, Eficent, Odoo Community Association (OCA)
Author-email: support@odoo-community.org
License: AGPL-3
Platform: UNKNOWN
Classifier: Programming Language :: Python :: 2.7
Classifier: Framework :: Odoo
Classifier: License :: OSI Approved :: GNU Affero General Public License v3
Requires-Dist: odoo (<10.1dev,>=10.0)
